script/__init__.py
script/script.py
copy_windows_10_lock_screen_wallpaper-1.1.4.dist-info/LICENSE
copy_windows_10_lock_screen_wallpaper-1.1.4.dist-info/METADATA
copy_windows_10_lock_screen_wallpaper-1.1.4.dist-info/WHEEL
copy_windows_10_lock_screen_wallpaper-1.1.4.dist-info/entry_points.txt
copy_windows_10_lock_screen_wallpaper-1.1.4.dist-info/top_level.txt
copy_windows_10_lock_screen_wallpaper-1.1.4.dist-info/RECORD
