Metadata-Version: 2.1
Name: copy-windows-10-lock-screen-wallpaper
Version: 1.1.4
Summary: Copy Windows 10 Lock Screen Wallpaper
Home-page: https://github.com/seehait/copy-windows-10-lock-screen-wallpaper
License: MIT
Platform: windows
Classifier: Development Status :: 5 - Production/Stable
Classifier: Intended Audience :: End Users/Desktop
Classifier: License :: OSI Approved :: MIT License
Classifier: Programming Language :: Python :: 3 :: Only
Classifier: Topic :: Utilities
Classifier: Operating System :: Microsoft :: Windows :: Windows 10
